robocupRAI/__init__.py
robocupRAI/config.py
robocupRAI/insert.py
robocupRAI/query.py
robocupRAI-1.6.dist-info/LICENSE.txt
robocupRAI-1.6.dist-info/METADATA
robocupRAI-1.6.dist-info/WHEEL
robocupRAI-1.6.dist-info/top_level.txt
robocupRAI-1.6.dist-info/RECORD
