Metadata-Version: 2.1
Name: robocupRAI
Version: 1.6
Summary: A small example package MongoDB Robo
Home-page: https://github.com/whaly-w/robocup
Author: whaly
Author-email: whalykj@gmail.com
Classifier: Programming Language :: Python :: 3
Classifier: License :: OSI Approved :: MIT License
Classifier: Operating System :: OS Independent
License-File: LICENSE.txt
Requires-Dist: dnspython
Requires-Dist: install
Requires-Dist: pymongo
